thunsearch/_thunsearch.cpython-38-x86_64-linux-gnu.so
thunsearch/__init__.py
thunsearch-0.0.1.dist-info/METADATA
thunsearch-0.0.1.dist-info/WHEEL
thunsearch-0.0.1.dist-info/top_level.txt
thunsearch-0.0.1.dist-info/LICENSE
thunsearch-0.0.1.dist-info/RECORD
